airports_pipeline_modules/__init__.py
airports_pipeline_modules/csv_parser/__init__.py
airports_pipeline_modules/csv_parser/parser.py
airports_pipeline_modules/ddlh/__init__.py
airports_pipeline_modules/ddlh/ddlh.py
airports_pipeline_modules/download/__init__.py
airports_pipeline_modules/download/download.py
airports_pipeline_modules/form/__init__.py
airports_pipeline_modules/form/form.py
airports_pipeline_modules/log_config/__init__.py
airports_pipeline_modules/log_config/log_config.py
airports_pipeline_modules/main_config/__init__.py
airports_pipeline_modules/main_config/main_config.py
airports_pipeline_modules/postgres/__init__.py
airports_pipeline_modules/postgres/postgres.py
airports_pipeline_modules/scripts/__init__.py
airports_pipeline_modules/scripts/scripts.py
airports_pipeline_modules/upload/__init__.py
airports_pipeline_modules/upload/upload.py
airports_pipeline_modules-1.0.8.dist-info/LICENSE
airports_pipeline_modules-1.0.8.dist-info/METADATA
airports_pipeline_modules-1.0.8.dist-info/WHEEL
airports_pipeline_modules-1.0.8.dist-info/top_level.txt
airports_pipeline_modules-1.0.8.dist-info/RECORD
