Metadata-Version: 2.1
Name: airports_pipeline_modules
Version: 1.0.8
Summary: Custom modules for airports data pipeline
Author-email: Baris Saltik <baris.saltik@dell.com>
Project-URL: Homepage, https://github.com/baris-saltik/airports-pipeline
Classifier: Programming Language :: Python :: 3
Classifier: License :: OSI Approved :: MIT License
Classifier: Operating System :: OS Independent
Requires-Python: >=3.8
License-File: LICENSE
